bioplot/__init__.py
bioplot/bioplot.py
bioplot-0.0.2.dist-info/METADATA
bioplot-0.0.2.dist-info/RECORD
bioplot-0.0.2.dist-info/WHEEL
bioplot-0.0.2.dist-info/top_level.txt
