Metadata-Version: 2.1
Name: bioplot
Version: 0.0.2
Summary: to create figures for biology.
Home-page: UNKNOWN
Author: Koji Ono
Author-email: koji.ono@exwzd.com
License: UNKNOWN
Platform: UNKNOWN
Classifier: Programming Language :: Python :: 3.6
Requires-Python: >3.6
Requires-Dist: matplotlib
